fugashi_plus.libs/libmecab-9a298cb7.so.2.0.0
fugashi/fugashi.cpython-312-x86_64-linux-gnu.so
fugashi/__init__.py
fugashi/fugashi.pyi
fugashi/cli.py
fugashi/py.typed
fugashi_plus-1.4.0.post1.dist-info/top_level.txt
fugashi_plus-1.4.0.post1.dist-info/RECORD
fugashi_plus-1.4.0.post1.dist-info/LICENSE
fugashi_plus-1.4.0.post1.dist-info/entry_points.txt
fugashi_plus-1.4.0.post1.dist-info/LICENSE.mecab
fugashi_plus-1.4.0.post1.dist-info/METADATA
fugashi_plus-1.4.0.post1.dist-info/WHEEL
