Metadata-Version: 2.1
Name: fugashi-plus
Version: 1.4.0.post1
Summary: A Cython MeCab wrapper for fast, pythonic Japanese tokenization and morphological analysis with additional improvements.
Home-page: https://github.com/tsukumijima/fugashi-plus
Author: Paul O'Leary McCann
Author-email: polm@dampfkraft.com
License: MIT
Classifier: Environment :: Console
Classifier: Intended Audience :: Developers
Classifier: Intended Audience :: Science/Research
Classifier: License :: OSI Approved :: MIT License
Classifier: Natural Language :: Japanese
Classifier: Operating System :: POSIX :: Linux
Classifier: Operating System :: MacOS :: MacOS X
Classifier: Operating System :: Microsoft :: Windows
Classifier: Programming Language :: Python :: 3
Classifier: Programming Language :: Python :: 3.8
Classifier: Programming Language :: Python :: 3.9
Classifier: Programming Language :: Python :: 3.10
Classifier: Programming Language :: Python :: 3.11
Classifier: Programming Language :: Python :: 3.12
Classifier: Programming Language :: Python :: 3.13
Classifier: Programming Language :: Cython
Classifier: Topic :: Text Processing :: Linguistic
Classifier: Typing :: Typed
Requires-Python: >=3.8
License-File: LICENSE
License-File: LICENSE.mecab
Provides-Extra: unidic
Requires-Dist: unidic; extra == "unidic"
Provides-Extra: unidic-lite
Requires-Dist: unidic-lite; extra == "unidic-lite"
